harrys_toolbox/__init__.py
harrys_toolbox/_fps_counter.py
harrys_toolbox/_milliseconds.py
harrys_toolbox-1.0.1.dist-info/licenses/LICENSE
harrys_toolbox-1.0.1.dist-info/METADATA
harrys_toolbox-1.0.1.dist-info/WHEEL
harrys_toolbox-1.0.1.dist-info/top_level.txt
harrys_toolbox-1.0.1.dist-info/RECORD
