Metadata-Version: 2.4
Name: harrys-toolbox
Version: 1.0.1
Summary: Harry's Toolbox is a collection of lightweight Python utilities. Each designed to simplify a basic task, such as calculating the framerate of a video feed.
Author: Harry Boyd
License: Copyright 2025 Harry Boyd
Project-URL: Homepage, https://github.com/HBoyd255/harrys-toolbox
Classifier: Programming Language :: Python :: 3
Classifier: License :: OSI Approved :: MIT License
Classifier: Operating System :: OS Independent
License-File: LICENSE
Dynamic: license-file
